new_news_api/__init__.py
new_news_api/my_news.py
news_api_library-0.1.dist-info/METADATA
news_api_library-0.1.dist-info/WHEEL
news_api_library-0.1.dist-info/top_level.txt
news_api_library-0.1.dist-info/RECORD
